sgr_agent_core/__init__.py
sgr_agent_core/agent_config.py
sgr_agent_core/agent_definition.py
sgr_agent_core/agent_factory.py
sgr_agent_core/base_agent.py
sgr_agent_core/base_tool.py
sgr_agent_core/models.py
sgr_agent_core/next_step_tool.py
sgr_agent_core/stream.py
sgr_agent_core/agents/__init__.py
sgr_agent_core/agents/sgr_agent.py
sgr_agent_core/agents/sgr_tool_calling_agent.py
sgr_agent_core/agents/tool_calling_agent.py
sgr_agent_core/prompts/__init__.py
sgr_agent_core/prompts/clarification_response.txt
sgr_agent_core/prompts/initial_user_request.txt
sgr_agent_core/prompts/research_system_prompt.txt
sgr_agent_core/prompts/system_prompt.txt
sgr_agent_core/server/__init__.py
sgr_agent_core/server/__main__.py
sgr_agent_core/server/app.py
sgr_agent_core/server/endpoints.py
sgr_agent_core/server/models.py
sgr_agent_core/server/settings.py
sgr_agent_core/services/__init__.py
sgr_agent_core/services/mcp_service.py
sgr_agent_core/services/prompt_loader.py
sgr_agent_core/services/registry.py
sgr_agent_core/services/tavily_search.py
sgr_agent_core/tools/__init__.py
sgr_agent_core/tools/adapt_plan_tool.py
sgr_agent_core/tools/clarification_tool.py
sgr_agent_core/tools/create_report_tool.py
sgr_agent_core/tools/extract_page_content_tool.py
sgr_agent_core/tools/final_answer_tool.py
sgr_agent_core/tools/generate_plan_tool.py
sgr_agent_core/tools/reasoning_tool.py
sgr_agent_core/tools/web_search_tool.py
sgr_agent_core-0.6.0.dist-info/licenses/LICENSE
sgr_agent_core-0.6.0.dist-info/METADATA
sgr_agent_core-0.6.0.dist-info/WHEEL
sgr_agent_core-0.6.0.dist-info/entry_points.txt
sgr_agent_core-0.6.0.dist-info/top_level.txt
sgr_agent_core-0.6.0.dist-info/RECORD
