Metadata-Version: 2.4
Name: sgr-agent-core
Version: 0.6.0
Summary: SGR Agent Core - Schema-Guided Reasoning for building agent
Author: virrius, VaKovaLskii, abdullin, EvilFreelancer, Shadekss, mixaill76
License: MIT
Project-URL: Homepage, https://github.com/vamplabAI/sgr-agent-core
Project-URL: Repository, https://github.com/vamplabAI/sgr-agent-core
Project-URL: Issues, https://github.com/vamplabAI/sgr-agent-core/issues
Project-URL: Documentation, https://vamplabai.github.io/sgr-agent-core/
Project-URL: SGR Concept Creator - @abdullin, https://t.me/llm_under_hood
Project-URL: Coordinator - @VaKovaLskii, https://t.me/neuraldeep
Project-URL: Core Developer - @virrius, https://t.me/virrius_tech
Project-URL: Core Developer - @EvilFreelancer, https://t.me/evilfreelancer
Project-URL: DevOps & Deployment - @mixaill76, https://t.me/mixaill76
Project-URL: Hybrid FC research - @Shadekss, https://t.me/Shadekss
Keywords: ai,research,reasoning,schema-guided,openai
Classifier: Development Status :: 3 - Alpha
Classifier: Intended Audience :: Developers
Classifier: Intended Audience :: Science/Research
Classifier: License :: OSI Approved :: MIT License
Classifier: Programming Language :: Python :: 3
Classifier: Programming Language :: Python :: 3.11
Classifier: Programming Language :: Python :: 3.12
Classifier: Programming Language :: Python :: 3.13
Classifier: Topic :: Scientific/Engineering :: Artificial Intelligence
Classifier: Topic :: Software Development :: Libraries :: Python Modules
Requires-Python: >=3.11
License-File: LICENSE
Requires-Dist: PyYAML>=6.0
Requires-Dist: python-dateutil>=2.8.0
Requires-Dist: pydantic>=2.0.0
Requires-Dist: pydantic-settings>=2.10.1
Requires-Dist: openai>=1.0.0
Requires-Dist: httpx[socks]>=0.25.0
Requires-Dist: tavily-python>=0.3.0
Requires-Dist: fastapi>=0.116.1
Requires-Dist: uvicorn>=0.35.0
Requires-Dist: fastmcp>=2.12.4
Requires-Dist: jambo>=0.1.3.post2
Provides-Extra: dev
Requires-Dist: pytest>=7.0.0; extra == "dev"
Requires-Dist: pytest-cov>=4.0.0; extra == "dev"
Requires-Dist: pytest-asyncio>=0.21.0; extra == "dev"
Requires-Dist: black>=23.0.0; extra == "dev"
Requires-Dist: isort>=5.12.0; extra == "dev"
Requires-Dist: flake8>=6.0.0; extra == "dev"
Requires-Dist: mypy>=1.0.0; extra == "dev"
Provides-Extra: tests
Requires-Dist: pytest>=7.0.0; extra == "tests"
Requires-Dist: pytest-cov>=4.0.0; extra == "tests"
Requires-Dist: pytest-asyncio>=0.21.0; extra == "tests"
Dynamic: license-file
